[
    {
        "table": "text_data",
        "field": "text",
        "specifier": "category",
        "files": {
            "common": null,
            "miscellaneous": null,
            "uma-title": 5,
            "uma-name": 6,
            "item-name": 23,
            "item-desc": 24,
            "skill-name": 47,
            "skill-desc": 48,
            "race-name": [28, 29, 32, 33, 36, 111],
            "trainer-title": 65,
            "trainer-title-requirements": 66,
            "missions": 67,
            "support-title": 76,
            "advice": 97,
            "uma-nickname": 130,
            "uma-nickname-requirements": 131,
            "pvp-raw-score-name": 140,
            "pvp-raw-score-desc": 141,
            "conditions-name": 142,
            "conditions-desc": 143,
            "pvp-score-bonus-name": 148,
            "story-event-missions": 190,
            "support-effect-unique-desc": 155,
            "item-acquisition-methods-shop": 25,
            "factor-desc": 172,
            "support-bonus": 186,
            "help": 63,
            "predictions": 27,
            "mission-groups": 187,
            "gacha-info": 13,
            "gacha-names": 26,
            "presents-desc": 64,
            "item-uma-pieces": 113,
            "uma-profile-tagline": 144,
            "uma-profile-weight": 9,
            "campaigns": 70,
            "special-transfer-name": 215,
            "special-transfer-desc": 216,
            "special-transfer-requirements": 217,
            "special-transfer-thanks": 220,
            "load-screens": 69,
            "support-effect-unique-name": 150,
            "support-effect-name": 151,
            "support-effect-desc": 154,
            "support-full-name": 75,
            "tutorial-text": 3,
            "song-desc": 128,
            "static-uma-profile": 175,
            "jukebox-comments": 228,
            "scenario-desc": 120,
            "scenario-item-name": 225,
            "scenario-item-desc-long": 226,
            "scenario-item-desc-short": 238,
            "story-titles-mainstory": 94,
            "story-titles-events": 191,
            "story-titles-umas": 92,
            "mob-name": 59,
            "scenario-effects": [198, 199, 200]
        },
        "overrides": {
            "skill_data": ["skill-desc", "alt/skill-desc"]
        }
    },
    {
        "table": "race_jikkyo_comment",
        "field": "message",
        "file": "race_jikkyo_comment"
    },
    {
        "table": "race_jikkyo_message",
        "field": "message",
        "file": "race_jikkyo_message"
    },
    {
        "table": "character_system_text",
        "field": "text",
        "specifier": "character_id",
        "subdir": true,
        "files": {
            "ines": 1031,
            "tachyon": 1032
        }
    }
]