[
    {
        "re": "\\b(?-i:He)\\b",
        "repl": "She",
        "limit": true
    },
    {
        "re": "\\b(?-i:he)\\b",
        "repl": "she",
        "limit": true
    },
    {
        "re": "\\b(h|H)i[sm]\\b",
        "repl": "\\1er",
        "limit": true
    },
    {
        "re": "himself",
        "repl": "herself",
        "limit": true
    },
    {
        "re": "Mr.",
        "repl": "Ms.",
        "limit": true
    },
    {
        "re": "baba",
        "repl": "field"
    },
    {
        "re": "(?:To?re?sen|Trespass(?:ing|er)) (?:Academy|Gakuen)",
        "repl": "Tracen Academy"
    },
    {
        "re": "Aohar Cup",
        "repl": "Aoharu Hai"
    },
    {
        "re": "selection race",
        "repl": "Selection Race"
    },
    {
        "re": "make-?(?:out|up) debut",
        "repl": "debut"
    },
    {
        "re": "(?:Yuuma|Arima) (?:Memorial)",
        "repl": "Arima Kinen"
    },
    {
        "re": "Emperor's prize",
        "repl": "Tennou Sho"
    },
    {
        "re": "Simbolildorf",
        "repl": "Symboli Rudolf"
    },
    {
        "re": "Chayahide",
        "repl": "Hayahide"
    },
    {
        "re": "Tysin",
        "repl": "Taishin"
    },
    {
        "re": "Ba(?:x|ks)ing?",
        "repl": "Bakushin"
    },
    {
        "re": "Bakushin[- ]o",
        "repl": "Bakushin O"
    },
    {
        "re": "Reis[sc]h(?:ow|au)er",
        "repl": "Rice Shower"
    },
    {
        "re": "The Rice Showers?",
        "repl": "Rice Shower"
    },
    {
        "re": "MedillomacQueen",
        "repl": "Mejiro McQueen"
    },
    {
        "re": "Tamamocross",
        "repl": "Tamamo Cross"
    },
    {
        "re": "(?:my )?balls",
        "repl": "Tama",
        "limit": true
    },
    {
        "re": "Gold Chichee",
        "repl": "Gold City"
    },
    {
        "re": "Cici|Shichi",
        "repl": "City",
        "limit": true
    },
    {
        "re": "Yuki no Bijin|Yukinobidine",
        "repl": "Yukino Bijin"
    },
    {
        "re": "Daitak Helios",
        "repl": "Daitaku Helios"
    },
    {
        "re": "D(?:ai|e)wa ?scarl?ett?",
        "repl": "Daiwa Scarlet"
    },
    {
        "re": "Hishi[y\\-]?amazon",
        "repl": "Hishi Amazon"
    },
    {
        "re": "Neycha",
        "repl": "Nature",
        "limit": true
    },
    {
        "re": "[Ea]ish?in ?Fl[ua]sh",
        "repl": "Eishin Flash"
    },
    {
        "re": "Ma(?:ch|t)ikane Fuku(?:ki)?ta(?:r|l)u?",
        "repl": "Matikanefukukitaru"
    },
    {
        "re": "Fukk?u(?:ki)?talu?",
        "repl": "Fukukitaru"
    },
    {
        "re": "Sh?inkouindi",
        "repl": "Shinko Windy"
    },
    {
        "re": "Smboli",
        "repl": "Symboli"
    },
    {
        "re": "Haluurara",
        "repl": "Haru Urara"
    },
    {
        "re": "U[rl]all?a",
        "repl": "Urara"
    },
    {
        "re": "Gorsh?in?",
        "repl": "Golshi",
        "limit": true
    },
    {
        "re": "Glass Wonder",
        "repl": "Grass Wonder",
        "limit": true
    },
    {
        "re": "Te[ye]mu?-?",
        "repl": "TM",
        "limit": true
    },
    {
        "re": "(Opera|Bakushin)-Oh?",
        "repl": "\\1 O"
    },
    {
        "re": "El Condor Passer",
        "repl": "El Condor Pasa"
    },
    {
        "re": "Michonobourbon",
        "repl": "Mihono Bourbon"
    },
    {
        "re": "Inariwan",
        "repl": "Inari One"
    },
    {
        "re": "og[rl]ycap",
        "repl": "Oguri Cap"
    },
    {
        "re": "ogry",
        "repl": "Oguri"
    },
    {
        "re": "\\bSupe\\b",
        "repl": "Spe",
        "limit": true
    },
    {
        "re": "the horse girl in charge",
        "repl": "your horse girl",
        "limit": true
    },
    {
        "re": "Umadolu",
        "repl": "Umadol",
        "limit": true
    },
    {
        "re": "Siraoqui-sama",
        "repl": "Shiraoki-sama"
    },
    {
        "re": " ?\\.+ ?\\.+",
        "repl": "…"
    },
    {
        "re": "[,:]?…[,:]?",
        "repl": "…"
    },
    {
        "re": "--+|――",
        "repl": "—"
    },
    {
        "re": " at…",
        "repl": "…",
        "limit": true
    },
    {
        "re": "　| {2,}",
        "repl": " "
    },
    {
        "re": "([a-z])…([a-z])",
        "repl": "\\1… \\2"
    },
    {
        "re": " *\\n *",
        "repl": " \\n"
    },
    {
        "re": "^ *\\n?",
        "repl": ""
    }
]